asynconsumer/__init__.py
asynconsumer/core.py
asynconsumer/samples/__init__.py
asynconsumer/samples/gcs_downloader.py
asynconsumer/samples/http_downloader.py
asynconsumer/samples/nop.py
asynconsumer-1.0.5.dist-info/LICENSE
asynconsumer-1.0.5.dist-info/METADATA
asynconsumer-1.0.5.dist-info/WHEEL
asynconsumer-1.0.5.dist-info/top_level.txt
asynconsumer-1.0.5.dist-info/RECORD
