Metadata-Version: 2.1
Name: asynconsumer
Version: 1.0.5
Summary: asynconsumer is a simple library for processing each items within iterable using asyncio.
Home-page: https://github.com/rhoboro/asynconsumer
Author: rhoboro
Author-email: rhoboro@gmail.com
Maintainer: rhoboro
Maintainer-email: rhoboro@gmail.com
License: Apache License 2.0
Platform: UNKNOWN
Classifier: Programming Language :: Python :: 3
Classifier: Programming Language :: Python :: 3.5
Classifier: Programming Language :: Python :: 3.6
Classifier: Programming Language :: Python :: 3.7
